LICENSE
MANIFEST.in
README.md
setup.py
mview/__init__.py
mview/tool.py
mview.egg-info/PKG-INFO
mview.egg-info/SOURCES.txt
mview.egg-info/dependency_links.txt
mview.egg-info/requires.txt
mview.egg-info/top_level.txt