Metadata-Version: 1.1
Name: mview
Version: 0.1.1
Summary: Package to show graphic view of pandas.DataFrame.
Home-page: https://github.com/hanzhichao2000/mview
Author: Zhichao HAN
Author-email: hanzhichao2000@foxmail.com
License: LGPL
Keywords: matrix view data frame
Platform: UNKNOWN
Classifier: Programming Language :: Python
Classifier: Topic :: Scientific/Engineering :: Visualization
